omnillm-0.2.2.dist-info/METADATA
omnillm-0.2.2.dist-info/WHEEL
omnillm-0.2.2.dist-info/entry_points.txt
omnillm-0.2.2.dist-info/licenses/LICENSE
omnillm/__init__.py
omnillm/anthropic.py
omnillm/base.py
omnillm/message.py
omnillm/openai.py
omnillm/utils.py
omnillm-0.2.2.dist-info/RECORD
