Metadata-Version: 2.1
Name: omnillm
Version: 0.2.2
Summary: A unified LLM API utility package.
Author-Email: Zsbyqx20 <112002598+Zsbyqx20@users.noreply.github.com>
License: Apache-2.0
Classifier: Development Status :: 3 - Alpha
Classifier: License :: OSI Approved :: Apache Software License
Classifier: Programming Language :: Python :: 3
Classifier: Programming Language :: Python :: 3.12
Classifier: Intended Audience :: Developers
Classifier: Intended Audience :: Science/Research
Classifier: Topic :: Software Development :: Libraries
Classifier: Topic :: Scientific/Engineering :: Artificial Intelligence
Requires-Python: >=3.12
Requires-Dist: openai>=1.54.4
Requires-Dist: anthropic>=0.39.0
Requires-Dist: python-dotenv>=1.0.1
Requires-Dist: httpx[socks]>=0.27.2
Requires-Dist: pillow>=11.0.0
Requires-Dist: requests>=2.32.3
